cascade/__init__.py
cascade/version.py
cascade/base/__init__.py
cascade/base/cache.py
cascade/base/config.py
cascade/base/meta_handler.py
cascade/base/serialization.py
cascade/base/traceable.py
cascade/base/utils.py
cascade/cli/__init__.py
cascade/cli/artifact.py
cascade/cli/cli.py
cascade/cli/comment.py
cascade/cli/common.py
cascade/cli/desc.py
cascade/cli/query.py
cascade/cli/run.py
cascade/cli/tag.py
cascade/cli/ui.py
cascade/cli/view.py
cascade/data/__init__.py
cascade/data/apply_modifier.py
cascade/data/bruteforce_cacher.py
cascade/data/composer.py
cascade/data/concatenator.py
cascade/data/cyclic_sampler.py
cascade/data/data_card.py
cascade/data/dataset.py
cascade/data/filter.py
cascade/data/folder_dataset.py
cascade/data/functions.py
cascade/data/modifier.py
cascade/data/pickler.py
cascade/data/random_sampler.py
cascade/data/range_sampler.py
cascade/data/schema.py
cascade/data/sequential_cacher.py
cascade/data/simple_dataloader.py
cascade/data/utils.py
cascade/data/validation.py
cascade/data/version_assigner.py
cascade/lines/__init__.py
cascade/lines/data_line.py
cascade/lines/disk_line.py
cascade/lines/line.py
cascade/lines/model_line.py
cascade/meta/__init__.py
cascade/meta/data_registrator.py
cascade/meta/hashes.py
cascade/meta/history_viewer.py
cascade/meta/meta_viewer.py
cascade/meta/metric_viewer.py
cascade/meta/server.py
cascade/meta/utils.py
cascade/meta/diff_viewer/__init__.py
cascade/meta/diff_viewer/base_diff_viewer.py
cascade/meta/diff_viewer/dataset_version_diff_viewer.py
cascade/meta/diff_viewer/diff_viewer.py
cascade/meta/diff_viewer/repo_diff_viewer.py
cascade/meta/diff_viewer/workspace_diff_viewer.py
cascade/metrics/__init__.py
cascade/metrics/metric.py
cascade/metrics/classification/__init__.py
cascade/metrics/classification/accuracy.py
cascade/models/__init__.py
cascade/models/basic_model.py
cascade/models/model.py
cascade/models/model_line.py
cascade/models/model_repo.py
cascade/models/trainer.py
cascade/models/workspace.py
cascade_ml-0.16.0.dist-info/licenses/LICENSE
cascade_ml-0.16.0.dist-info/METADATA
cascade_ml-0.16.0.dist-info/WHEEL
cascade_ml-0.16.0.dist-info/entry_points.txt
cascade_ml-0.16.0.dist-info/top_level.txt
cascade_ml-0.16.0.dist-info/RECORD
