Metadata-Version: 2.4
Name: cascade-ml
Version: 0.16.0
Summary: ML-Engineering library
Home-page: https://github.com/oxid15/cascade
Author: Ilia Moiseev
Author-email: ilia.moiseev.5@yandex.ru
License: Apache License 2.0
Project-URL: Documentation, https://oxid15.github.io/cascade/en/latest/index.html
Classifier: Programming Language :: Python :: 3
Classifier: Operating System :: OS Independent
Requires-Python: >=3.7
License-File: LICENSE
Requires-Dist: tqdm>=4.64.1
Requires-Dist: numpy>=1.18.5
Requires-Dist: pandas>=1.1.5
Requires-Dist: deepdiff<8.4.0,>=5.0.2
Requires-Dist: pendulum>=2.1.2
Requires-Dist: pyyaml>=5.4.1
Requires-Dist: coolname>=2.0.0
Requires-Dist: click>=8.0.0
Requires-Dist: typing-extensions<5,>=4.1.1
Requires-Dist: astunparse; python_version < "3.9"
Requires-Dist: orderly-set==5.3.2; python_version == "3.8"
Provides-Extra: opencv
Requires-Dist: opencv-python; extra == "opencv"
Provides-Extra: pandera
Requires-Dist: pandera[io]<1,>=0.6.5; extra == "pandera"
Provides-Extra: pil
Requires-Dist: Pillow<11,>=8.4.0; extra == "pil"
Provides-Extra: pydantic
Requires-Dist: pydantic<3,>=1.9.2; extra == "pydantic"
Provides-Extra: sklearn
Requires-Dist: scikit-learn<2,>=0.24.2; extra == "sklearn"
Provides-Extra: torch
Requires-Dist: torch<3,>=1.10.2; extra == "torch"
Provides-Extra: view
Requires-Dist: dash<3; extra == "view"
Requires-Dist: plotly>=5.7.0; extra == "view"
Requires-Dist: dash-renderjson==0.0.1; extra == "view"
Provides-Extra: all
Requires-Dist: Pillow<11,>=8.4.0; extra == "all"
Requires-Dist: scikit-learn<2,>=0.24.2; extra == "all"
Requires-Dist: dash-renderjson==0.0.1; extra == "all"
Requires-Dist: plotly>=5.7.0; extra == "all"
Requires-Dist: pandera[io]<1,>=0.6.5; extra == "all"
Requires-Dist: torch<3,>=1.10.2; extra == "all"
Requires-Dist: pydantic<3,>=1.9.2; extra == "all"
Requires-Dist: opencv-python; extra == "all"
Requires-Dist: dash<3; extra == "all"
Dynamic: author
Dynamic: author-email
Dynamic: classifier
Dynamic: description
Dynamic: description-content-type
Dynamic: home-page
Dynamic: license
Dynamic: license-file
Dynamic: project-url
Dynamic: provides-extra
Dynamic: requires-dist
Dynamic: requires-python
Dynamic: summary
